Metadata-Version: 2.1
Name: flower-oauth-azure
Version: 1.0
Summary: Azure Oauth support for Flower
Home-page: https://github.com/saxix/flower_oauth_azure
Author: 
Author-email: 
License: MIT
Platform: UNKNOWN
Classifier: Development Status :: 3 - Alpha
Classifier: Natural Language :: English
Classifier: Programming Language :: Python :: 3.6
Provides-Extra: verification
